polylabel/__init__.py
python_polylabel-0.6.dist-info/METADATA
python_polylabel-0.6.dist-info/RECORD
python_polylabel-0.6.dist-info/WHEEL
python_polylabel-0.6.dist-info/top_level.txt
