Metadata-Version: 2.1
Name: python-polylabel
Version: 0.6
Summary: Port of polylabel (made by MapBox - https://github.com/mapbox/polylabel)
Home-page: UNKNOWN
Author: Michal Hatak
Author-email: me@twista.cz
License: UNKNOWN
Platform: UNKNOWN
